sphinx_clutter/__init__.py
sphinx_clutter/ext.py
sphinx_clutter_bazbazoo-0.0.1.dist-info/LICENSE
sphinx_clutter_bazbazoo-0.0.1.dist-info/METADATA
sphinx_clutter_bazbazoo-0.0.1.dist-info/WHEEL
sphinx_clutter_bazbazoo-0.0.1.dist-info/top_level.txt
sphinx_clutter_bazbazoo-0.0.1.dist-info/RECORD
