Metadata-Version: 2.1
Name: sphinx-clutter-bazbazoo
Version: 0.0.1
Summary: Sphinx Clutter plugin
Home-page: https://github.com/cluttercode/sphinx-clutter
Author: Itay Donanhirsh
Author-email: itay.donanhirsh@checkr.com
License: UNKNOWN
Platform: UNKNOWN
Classifier: Programming Language :: Python :: 3
Classifier: License :: OSI Approved :: Apache Software License
Classifier: Operating System :: OS Independent
Requires-Python: >=3.6
